ayon_api/__init__.py
ayon_api/_api.py
ayon_api/constants.py
ayon_api/entity_hub.py
ayon_api/events.py
ayon_api/exceptions.py
ayon_api/graphql.py
ayon_api/graphql_queries.py
ayon_api/operations.py
ayon_api/server_api.py
ayon_api/typing.py
ayon_api/utils.py
ayon_api/version.py
ayon_api/_api_helpers/__init__.py
ayon_api/_api_helpers/actions.py
ayon_api/_api_helpers/activities.py
ayon_api/_api_helpers/attributes.py
ayon_api/_api_helpers/base.py
ayon_api/_api_helpers/bundles_addons.py
ayon_api/_api_helpers/dependency_packages.py
ayon_api/_api_helpers/events.py
ayon_api/_api_helpers/folders.py
ayon_api/_api_helpers/installers.py
ayon_api/_api_helpers/links.py
ayon_api/_api_helpers/lists.py
ayon_api/_api_helpers/products.py
ayon_api/_api_helpers/projects.py
ayon_api/_api_helpers/representations.py
ayon_api/_api_helpers/secrets.py
ayon_api/_api_helpers/tasks.py
ayon_api/_api_helpers/thumbnails.py
ayon_api/_api_helpers/versions.py
ayon_api/_api_helpers/workfiles.py
ayon_python_api-1.2.9.dist-info/licenses/LICENSE
ayon_python_api-1.2.9.dist-info/METADATA
ayon_python_api-1.2.9.dist-info/WHEEL
ayon_python_api-1.2.9.dist-info/top_level.txt
ayon_python_api-1.2.9.dist-info/RECORD
