Metadata-Version: 2.4
Name: ayon_python_api
Version: 1.2.9
Summary: AYON Python API
Home-page: https://github.com/ynput/ayon-python-api
Author: ynput.io
Author-email: "ynput.io" <info@ynput.io>
License:                                  Apache License
Project-URL: Repository, https://github.com/ynput/ayon-python-api
Project-URL: Changelog, https://github.com/ynput/ayon-python-api/releases
Keywords: AYON,ynput,OpenPype,vfx
Classifier: Development Status :: 5 - Production/Stable
Classifier: Programming Language :: Python
Classifier: Programming Language :: Python :: 3
License-File: LICENSE
Requires-Dist: requests>=2.27.1
Requires-Dist: Unidecode>=1.3.0
Dynamic: author
Dynamic: home-page
Dynamic: license-file
